webnew/__init__.py
webnew/request.py
webnew-1.1.1.dist-info/LICENSE
webnew-1.1.1.dist-info/METADATA
webnew-1.1.1.dist-info/WHEEL
webnew-1.1.1.dist-info/top_level.txt
webnew-1.1.1.dist-info/RECORD
