Metadata-Version: 2.1
Name: webnew
Version: 1.1.1
Summary: A light library to build tiny websites 一个用于搭建轻量级网站的库
Home-page: https://github.com/MinesomeBTQ/WebNew
Author: BT.Q
Author-email: 2264481688@qq.com
License: UNKNOWN
Platform: UNKNOWN
Classifier: Programming Language :: Python :: 3
Classifier: License :: OSI Approved :: MIT License
Classifier: Operating System :: OS Independent
License-File: LICENSE
Requires-Dist: web.py
